{
  "Neck": {
    "Length": {
      "Short": ["compact", "graceful", "sturdy", "slightly broad"],
      "Medium": ["balanced", "natural proportion", "softly defined", "elegant curve"],
      "Long": ["slender", "swan-like", "elongated", "graceful", "refined"]
    },
    "Thickness": {
      "Thin": ["delicate", "fine-boned", "slender line", "soft taper"],
      "Average": ["natural contour", "smooth definition", "even form"],
      "Thick": ["strong", "full", "robust", "sturdy base", "powerful presence"]
    },
    "Shape": {
      "Straight": ["clean vertical line", "slight taper", "refined contour"],
      "Curved": ["gentle inward arc", "graceful dip", "natural bend"],
      "Angular": ["sharp definition", "firm base angle", "toned muscle line"]
    },
    "Descriptors": [
      "smooth-skinned", "elegant", "refined", "youthful", "symmetrical", "soft shadowed", "defined clavicle transition"
    ]
  }
}
